<order>
    <details>
        <quantity>101</quantity>
        <bracket>108</bracket>
        <stock>(S30) Standard Smooth</stock>
        <foil>false</foil>
    </details>
    <fronts>
        <card>
            <id>1aR4QXZOW5O1EjRs-ov-PP-p1yxJK-K0t</id>
            <slots>0,1,2,3</slots>
            <name>Ajani, Nacatl Pariah [MH3] {237}.jpg</name>
            <query>ajani nacatl pariah</query>
        </card>
        <card>
            <id>15b7Op7sw4_oMNdWD7HNX__1NYYx1tKmA</id>
            <slots>4,5,6,7</slots>
            <name>Amped Raptor.png</name>
            <query>amped raptor</query>
        </card>
        <card>
            <id>1khUgi8iXY51icqhDsBHgv1Dzj2lQvBE7</id>
            <slots>8,9,10,11</slots>
            <name>Arid Mesa [ZEN] {211}.jpg</name>
            <query>arid mesa</query>
        </card>
        <card>
            <id>1V84AvxEn8UB4WcQq1q7-OJEdDNb3rluS</id>
            <slots>12</slots>
            <name>Blood Crypt (Borderless Engelbert Kerner x MidJourney AI).jpg</name>
            <query>blood crypt</query>
        </card>
        <card>
            <id>1_L8iG49bsZHtGuSilUiASwVnUnHnPkQn</id>
            <slots>13,14,15,16</slots>
            <name>Cavern of Souls.png</name>
            <query>cavern of souls</query>
        </card>
        <card>
            <id>1OXLPZoiwj1lTClu7GHRNOf9LGaebUDeg</id>
            <slots>17</slots>
            <name>Chthonian Nightmare [MH3] {83}.jpg</name>
            <query>chthonian nightmare</query>
        </card>
        <card>
            <id>1REfLtXPn_JHJiXgbjuKr3FD8jAGYfTXx</id>
            <slots>18</slots>
            <name>Demonic Tutor (Borderless Zack Stella).jpg</name>
            <query>demonic tutor</query>
        </card>
        <card>
            <id>1iTU7CnS3oZDm3CBFf4mODHAs2drJNvWZ</id>
            <slots>19</slots>
            <name>Elegant Parlor [MKM] {325} (1).jpg</name>
            <query>elegant parlor</query>
        </card>
        <card>
            <id>1Qbw8a4jBpBj_56Nb8anuLsYTs1hMTszl</id>
            <slots>20,21</slots>
            <name>Galvanic Discharge.png</name>
            <query>galvanic discharge</query>
        </card>
        <card>
            <id>1bf3L6_DxcXk1MLoXtNvHN9yqwEAjLuH3</id>
            <slots>22,23,24</slots>
            <name>Goblin Bombardment (Borderless Dave Kendall).jpg</name>
            <query>goblin bombardment</query>
        </card>
        <card>
            <id>1rVD90wnuMOmlLhzqQgItuvgN9TdljF5B</id>
            <slots>25</slots>
            <name>Godless Shrine (Borderless Jenn Ravenna).jpg</name>
            <query>godless shrine</query>
        </card>
        <card>
            <id>1hnZg7DfqepFGj_90YvnVTB-CTi_jUsO0</id>
            <slots>26,27,28,29</slots>
            <name>Guide of Souls.png</name>
            <query>guide of souls</query>
        </card>
        <card>
            <id>1KT-fBEta1yKqjBeyvZiKN_VpT7lk28Oj</id>
            <slots>30,51,52,67</slots>
            <name>Static Prison.png</name>
            <query>static prison</query>
        </card>
        <card>
            <id>16saKei6hGsOtTzeSRHFR5aKXpZDz_mM8</id>
            <slots>31</slots>
            <name>Mountain (SLD 66).jpg</name>
            <query>mountain</query>
        </card>
        <card>
            <id>1sD4IyV6RX2-OCdN47z4jDQLPU-COtJOl</id>
            <slots>32,33,34,35</slots>
            <name>Ocelot Pride (Borderless Joshua Cairos).jpg</name>
            <query>ocelot pride</query>
        </card>
        <card>
            <id>1KHniKCxmRPdlG4pvP67TqgGdQITbU81Q</id>
            <slots>36,37,38,39</slots>
            <name>Orcish Bowmasters (Borderless Maxim Kostin).jpg</name>
            <query>orcish bowmasters</query>
        </card>
        <card>
            <id>1ZhM7_WGank-rgRdTDVlxk4Zhza4rWlO1</id>
            <slots>40,41,42</slots>
            <name>Plains (UST 212).jpg</name>
            <query>plains</query>
        </card>
        <card>
            <id>1TYnGuv8fmDcYpjMqyM0VMBcEofHkfzSZ</id>
            <slots>43,44</slots>
            <name>Ragavan, Nimble Pilferer.jpg</name>
            <query>ragavan nimble pilferer</query>
        </card>
        <card>
            <id>1t2HCsfC0tesNTscUv390uNU4C6vZb5ZK</id>
            <slots>45,46,47,48</slots>
            <name>Sacred Foundry (Borderless Engelbert Kerner x MidJourney AI).jpg</name>
            <query>sacred foundry</query>
        </card>
        <card>
            <id>1QyP8qouUIwv7qtnFtkVymsa_ptLeXrX5</id>
            <slots>49</slots>
            <name>Savai Triome (a).png</name>
            <query>savai triome</query>
        </card>
        <card>
            <id>1Kf7IYFX8NIKyqBX0_BmVrRuwI7jvlJ9p</id>
            <slots>50</slots>
            <name>Shadowy Backstreet [MKM] {330} (1).jpg</name>
            <query>shadowy backstreet</query>
        </card>
        <card>
            <id>1_ebfbMOYrhc6tq3oD49TcrGTgD_waaJY</id>
            <slots>53</slots>
            <name>Swamp (BFZ 264).jpg</name>
            <query>swamp</query>
        </card>
        <card>
            <id>1s57fABp0vANomxlf8XER32Tabqa8J3kM</id>
            <slots>54,55,56,57</slots>
            <name>Swords to Plowshares (Borderless Jeff A. Menges).jpg</name>
            <query>swords to plowshares</query>
        </card>
        <card>
            <id>1k2De_OCaDhHRBpz38pSOp0WDVVAoig1o</id>
            <slots>58,59</slots>
            <name>Voice of Victory [TDM] {33}.jpg</name>
            <query>voice of victory</query>
        </card>
        <card>
            <id>15q4urPRxDuRgf0EJqvmGgERQsrMi1kCr</id>
            <slots>60,61</slots>
            <name>Containment Priest (Full).png</name>
            <query>containment priest</query>
        </card>
        <card>
            <id>1ha0n42Db-RlgXGqHElF1uBHI_4y7eDRl</id>
            <slots>62,63</slots>
            <name>Lithomantic Barrage.png</name>
            <query>lithomantic barrage</query>
        </card>
        <card>
            <id>1AXtQplbTbUtXe1NAz89OWMAjviMpoQ5n</id>
            <slots>64</slots>
            <name>Lurrus of the Dream-Den (Borderless Slawomir Maniak).jpg</name>
            <query>lurrus of dream den</query>
        </card>
        <card>
            <id>1uVcjd3ilK3PlFAXSqZGillfq6uIGmWzo</id>
            <slots>65</slots>
            <name>Prismatic Ending.jpg</name>
            <query>prismatic ending</query>
        </card>
        <card>
            <id>1LOmiuh_GhFCsalKx_yK4bgC6Sx7jpPQj</id>
            <slots>66</slots>
            <name>Prismatic Ending [SPG] {40}.jpg</name>
            <query>prismatic ending</query>
        </card>
        <card>
            <id>1xyMKvwQqTlx-iMGCtJS_ujJekJ4JI9AD</id>
            <slots>68,69,70</slots>
            <name>Thoughtseize (c).png</name>
            <query>thoughtseize</query>
        </card>
        <card>
            <id>1yh2_Pjsxp6Yjb65-5Fx_3An-M4GkLIdI</id>
            <slots>71,72,73,74</slots>
            <name>Vexing Bauble.png</name>
            <query>vexing bauble</query>
        </card>
        <card>
            <id>1WFU3KJnnRoBZNXB8hJyni2VvTkuQKdZp</id>
            <slots>75,76,77,78,79,80,81,82,83,84</slots>
            <name>Cat (SLD 28).jpg</name>
            <query>t:cat</query>
        </card>
        <card>
            <id>1MGU8sa926_jtesksbphnzO4tVqXNTJYu</id>
            <slots>85,86,87</slots>
            <name>Cat Warrior (Token) [MH3] {5}.jpg</name>
            <query>t:cat warrior</query>
        </card>
        <card>
            <id>1SMIpyvSVbicWU-fvmDnaazqNuEx3Uh9s</id>
            <slots>88</slots>
            <name>City's Blessing (TCMM 49).jpg</name>
            <query>t:citys blessing</query>
        </card>
        <card>
            <id>1L9fP_sp4rUUnVJoOVYEFuvK0LPwONpDq</id>
            <slots>89</slots>
            <name>Orc Army {5}.jpg</name>
            <query>t:orc army</query>
        </card>
        <card>
            <id>18QqsgqacaHbl5zbqeHcYW2KPA6RbCmys</id>
            <slots>90,91,92</slots>
            <name>Treasure (Olena Richards).jpg</name>
            <query>t:treasure</query>
        </card>
        <card>
            <id>1ZXOP0mLtkApfGaikdnabRc7kHEAeMUBv</id>
            <slots>93,94,95,96</slots>
            <name>Warrior (TDTK 1).jpg</name>
            <query>t:warrior</query>
        </card>
        <card>
            <id>1bKalFxjg7lWLH3niyJ2WG-DhwhsxU1zN</id>
            <slots>97,98,99,100</slots>
            <name>Sol Ring (Borderless Mike Bierek).jpg</name>
            <query>sol ring</query>
        </card>
    </fronts>
    <backs>
        <card>
            <id>1k9TUSQF8oCmyiWc225kT44J5Ltum9cwo</id>
            <slots>0,1,2,3</slots>
            <name>Ajani, Nacatl Avenger (a).png</name>
            <query>ajani nacatl avenger</query>
        </card>
    </backs>
    <cardback>1pHlYdcFBPBkPAsxi1Ebtx5By_ykoP_0v</cardback>
</order>
